_smoke/smoke.py
gatekeeper/__init__.py
gatekeeper/__main__.py
gatekeeper/engine.py
gatekeeper/version.py
gatekeeper/cli/__init__.py
gatekeeper/cli/main.py
gatekeeper/config/__init__.py
gatekeeper/config/loader.py
gatekeeper/explain/__init__.py
gatekeeper/explain/explain.py
gatekeeper/pr/__init__.py
gatekeeper/pr/format.py
gatekeeper_ai-0.1.7.dist-info/licenses/LICENSE
migrations/migration_base.py
migrations/v1_0_to_v1_1.py
submissions/broken.py
submissions/bug.py
submissions/example.py
submissions/good.py
submissions/has_secret.py
submissions/mycode.py
submissions/syntax_error.py
submissions/test_fail.py
submissions/will_fail.py
tests/test_policy_engine.py
whatsapp-bot/agents.py
whatsapp-bot/multi_judge.py
whatsapp-bot/repair.py
whatsapp-bot/repair_loop.py
gatekeeper_ai-0.1.7.dist-info/METADATA
gatekeeper_ai-0.1.7.dist-info/WHEEL
gatekeeper_ai-0.1.7.dist-info/entry_points.txt
gatekeeper_ai-0.1.7.dist-info/top_level.txt
gatekeeper_ai-0.1.7.dist-info/RECORD
