Metadata-Version: 2.4
Name: gatekeeper-ai
Version: 0.1.7
Summary: Deterministic code governance for CI and PRs
License: MIT License
Requires-Python: >=3.10
License-File: LICENSE
Dynamic: license-file
